Workbook

Sheet Summary
A1: Quiz Generator eval: 2026-09-11_1909
A3: How to use this file
A4: 1. Open the Results sheet: one row per question the AI wrote.
A5: 2. Fill in the yellow Y/N columns for every question. The Rubric sheet in the golden dataset explains each check.
A6: 3. Come back here: 'Your grades' fills itself in as you grade.
A7: 4. Take a screenshot of this sheet as your proof of evals.
A9: Run details
A10: Run | B10: 2026-09-11_1909
A11: Date | B11: 11 Sep 2026, 19:09
A12: Golden dataset | B12: quiz_generator_golden_v1.xlsx
A13: Rows run | B13: TC004, TC005, TC006, TC034, TC035, TC036, TC067, TC068, TC069, TC080, TC088, TC089, TC090, TC120, TC142
A14: Questions to grade | B14: 70
A15: Questions asked per row | B15: 5
A16: AI model | B16: Qwen/Qwen3-235B-A22B-Instruct-2507
A17: Answer checker | B17: on: a second AI re-solves every question without seeing the answer
A18: Curriculum | B18: des2@123.com (namespace math-grade6-ud58f81f0d50b)
A19: Database | B19: a temporary copy; the real database was not changed
A20: Time taken | B20: 6.1 minutes
A22: Automatic numbers (measured by the script)
A23: Metric | B23: Score | C23: Target | D23: Result | E23: How it is worked out
A24: Completion | B24: =IFERROR(COUNTIFS(Cases!$D$2:$D$16,"normal",Cases!$H$2:$H$16,"Y")/COUNTIF(Cases!$D$2:$D$16,"normal"),"") -> 1 | C24: 1 | D24: =IF(B24="","",IF(B24>=C24,"PASS","FAIL")) -> PASS | E24: Rows that returned every question they asked for (edge rows left out).
A25: Format pass rate | B25: =IFERROR(SUM(Cases!$J$2:$J$16)/SUM(Cases!$I$2:$I$16),"") -> 0.92207792 | C25: 0.9 | D25: =IF(B25="","",IF(B25>=C25,"PASS","FAIL")) -> PASS | E25: Of every question the AI drafted, the share that passed the format check first time.
A26: Checker agreement | B26: =IFERROR(SUM(Cases!$M$2:$M$16)/SUM(Cases!$L$2:$L$16),"") -> 0.98591549 | C26: 0.9 | D26: =IF(B26="","",IF(B26>=C26,"PASS","FAIL")) -> PASS | E26: Of every question checked, the share the independent checker solved to the same answer.
A27: Average attempts | B27: =IFERROR(AVERAGEIF(Cases!$D$2:$D$16,"normal",Cases!$P$2:$P$16),"") -> 1.4285714 | C27: 3 | D27: =IF(B27="","",IF(B27<=C27,"PASS","FAIL")) -> PASS | E27: Rounds of writing the agent needed per row. More rounds cost more.
A28: Worst letter balance | B28: =IF(COUNT(Cases!$R$2:$R$16)=0,"",MAX(Cases!$R$2:$R$16)) -> 0.4 | C28: 0.6 | D28: =IF(B28="","",IF(B28<=C28,"PASS","FAIL")) -> PASS | E28: The largest share of one answer letter in any row. High means guessable.
A29: True/false share | B29: =IFERROR(SUM(Cases!$S$2:$S$16)/SUM(Cases!$G$2:$G$16),"") -> 0.18571429 | C29: 0.3 | D29: =IF(B29="","",IF(B29<=C29,"PASS","FAIL")) -> PASS | E29: True/false questions among all questions (the agent allows at most 3 in 10).
A30: Bad input handled | B30: =IFERROR(COUNTIFS(Cases!$D$2:$D$16,"edge: expect error",Cases!$V$2:$V$16,"Y")/COUNTIF(Cases!$D$2:$D$16,"edge: expect error"),"") -> 1 | C30: 1 | D30: =IF(B30="","",IF(B30>=C30,"PASS","FAIL")) -> PASS | E30: Edge rows (like a topic that doesn't exist) that failed clearly, as they should.
A31: Average seconds per row | B31: =IFERROR(AVERAGEIF(Cases!$D$2:$D$16,"normal",Cases!$Q$2:$Q$16),"") -> 25.914286 | D31: record only | E31: Time per row, including the checker. Recorded, no target.
A33: Your grades (fill in the Results sheet)
A34: Check | B34: Score | C34: Graded (of 70) | D34: Target | E34: Result
A35: Correct key | B35: =IFERROR(COUNTIF(Results!$P$2:$P$71,"Y")/(COUNTIF(Results!$P$2:$P$71,"Y")+COUNTIF(Results!$P$2:$P$71,"N")),"") | C35: =COUNTIF(Results!$P$2:$P$71,"Y")+COUNTIF(Results!$P$2:$P$71,"N") -> 0 | D35: 0.98 | E35: =IF(C35=0,"not graded yet",IF(B35>=D35,"PASS","FAIL")) -> not graded yet
A36: One right answer | B36: =IFERROR(COUNTIF(Results!$Q$2:$Q$71,"Y")/(COUNTIF(Results!$Q$2:$Q$71,"Y")+COUNTIF(Results!$Q$2:$Q$71,"N")),"") | C36: =COUNTIF(Results!$Q$2:$Q$71,"Y")+COUNTIF(Results!$Q$2:$Q$71,"N") -> 0 | D36: 0.9 | E36: =IF(C36=0,"not graded yet",IF(B36>=D36,"PASS","FAIL")) -> not graded yet
A37: On topic | B37: =IFERROR(COUNTIF(Results!$R$2:$R$71,"Y")/(COUNTIF(Results!$R$2:$R$71,"Y")+COUNTIF(Results!$R$2:$R$71,"N")),"") | C37: =COUNTIF(Results!$R$2:$R$71,"Y")+COUNTIF(Results!$R$2:$R$71,"N") -> 0 | D37: 0.9 | E37: =IF(C37=0,"not graded yet",IF(B37>=D37,"PASS","FAIL")) -> not graded yet
A38: Right level | B38: =IFERROR(COUNTIF(Results!$S$2:$S$71,"Y")/(COUNTIF(Results!$S$2:$S$71,"Y")+COUNTIF(Results!$S$2:$S$71,"N")),"") | C38: =COUNTIF(Results!$S$2:$S$71,"Y")+COUNTIF(Results!$S$2:$S$71,"N") -> 0 | D38: 0.9 | E38: =IF(C38=0,"not graded yet",IF(B38>=D38,"PASS","FAIL")) -> not graded yet
A39: Good wrong answers | B39: =IFERROR(COUNTIF(Results!$T$2:$T$71,"Y")/(COUNTIF(Results!$T$2:$T$71,"Y")+COUNTIF(Results!$T$2:$T$71,"N")),"") | C39: =COUNTIF(Results!$T$2:$T$71,"Y")+COUNTIF(Results!$T$2:$T$71,"N") -> 0 | D39: 0.9 | E39: =IF(C39=0,"not graded yet",IF(B39>=D39,"PASS","FAIL")) -> not graded yet
A40: Good explanation | B40: =IFERROR(COUNTIF(Results!$U$2:$U$71,"Y")/(COUNTIF(Results!$U$2:$U$71,"Y")+COUNTIF(Results!$U$2:$U$71,"N")),"") | C40: =COUNTIF(Results!$U$2:$U$71,"Y")+COUNTIF(Results!$U$2:$U$71,"N") -> 0 | D40: 0.9 | E40: =IF(C40=0,"not graded yet",IF(B40>=D40,"PASS","FAIL")) -> not graded yet
A41: Good hint | B41: =IFERROR(COUNTIF(Results!$V$2:$V$71,"Y")/(COUNTIF(Results!$V$2:$V$71,"Y")+COUNTIF(Results!$V$2:$V$71,"N")),"") | C41: =COUNTIF(Results!$V$2:$V$71,"Y")+COUNTIF(Results!$V$2:$V$71,"N") -> 0 | D41: 0.9 | E41: =IF(C41=0,"not graded yet",IF(B41>=D41,"PASS","FAIL")) -> not graded yet
A42: Wrong keys the checker missed | B42: =COUNTIFS(Results!$P$2:$P$71,"N",Results!$N$2:$N$71,"agreed") -> 0 | C42: =COUNTIF(Results!$P$2:$P$71,"Y")+COUNTIF(Results!$P$2:$P$71,"N") -> 0 | D42: 0 | E42: =IF(C42=0,"not graded yet",IF(B42<=D42,"PASS","FAIL")) -> not graded yet
A43: A wrong key the checker agreed with is a mistake the automatic checker missed: it shows whether the checker can be trusted alone.

Sheet Results
A1: case_id | B1: topic | C1: level | D1: q# | E1: type | F1: question | G1: A | H1: B | I1: C | J1: D | K1: marked answer | L1: explanation | M1: hint | N1: checker verdict | O1: checker's answer | P1: Correct key | Q1: One right answer | R1: On topic | S1: Right level | T1: Good wrong answers | U1: Good explanation | V1: Good hint | W1: your comments | X1: learning objective | Y1: a good question looks like | Z1: must NOT include | AA1: skill tag
A2: TC004 | B2: 1.2 | C2: Easy | D2: 1 | E2: Multiple choice | F2: What is the value of -7 + 3? | G2: -10 | H2: 4 | I2: -4 | J2: 10 | K2: C) -4 | L2: You start at -7 and add 3, which means moving 3 units to the right on the number line. That brings you to -4. | M2: Start at -7. Adding 3 means move 3 to the right. | N2: agreed | O2: C | X2: Fluently add, subtract, multiply and divide integers. | Y2: One operation with negative integers, small numbers. | Z2: fractions or decimals (that's 1.5); exponents or roots (1.7) | AA2: add_integers
A3: TC004 | B3: 1.2 | C3: Easy | D3: 2 | E3: Multiple choice | F3: What is the result of -5 - 8? | G3: 3 | H3: -3 | I3: 13 | J3: -13 | K3: D) -13 | L3: Subtracting 8 from -5 means you go further left on the number line. -5 minus 8 is -13. | M3: Start at -5. Subtracting 8 means move 8 to the left. | N3: agreed | O3: D | X3: Fluently add, subtract, multiply and divide integers. | Y3: One operation with negative integers, small numbers. | Z3: fractions or decimals (that's 1.5); exponents or roots (1.7) | AA3: subtract_integers
A4: TC004 | B4: 1.2 | C4: Easy | D4: 3 | E4: Multiple choice | F4: What is -4 × 6? | G4: -24 | H4: 24 | I4: 10 | J4: -10 | K4: A) -24 | L4: When you multiply a negative number by a positive number, the result is negative. 4 times 6 is 24, so -4 times 6 is -24. | M4: Multiply 4 and 6, then make the answer negative because one number is negative. | N4: agreed | O4: A | X4: Fluently add, subtract, multiply and divide integers. | Y4: One operation with negative integers, small numbers. | Z4: fractions or decimals (that's 1.5); exponents or roots (1.7) | AA4: multiply_integers
A5: TC004 | B5: 1.2 | C5: Easy | D5: 4 | E5: Multiple choice | F5: What is -18 ÷ 3? | G5: 6 | H5: -6 | I5: 15 | J5: -21 | K5: B) -6 | L5: When you divide a negative number by a positive number, the result is negative. 18 divided by 3 is 6, so -18 divided by 3 is -6. | M5: Divide 18 by 3, then make the answer negative. | N5: agreed | O5: B | X5: Fluently add, subtract, multiply and divide integers. | Y5: One operation with negative integers, small numbers. | Z5: fractions or decimals (that's 1.5); exponents or roots (1.7) | AA5: divide_integers
A6: TC004 | B6: 1.2 | C6: Easy | D6: 5 | E6: True/False | F6: The sum of -9 and 9 is 0. | G6: True | H6: False | K6: A) True | L6: When you add a number and its opposite, the result is always 0. -9 and 9 are opposites, so their sum is 0. | M6: Think about what happens when you add a number to its opposite. | N6: agreed | O6: A | X6: Fluently add, subtract, multiply and divide integers. | Y6: One operation with negative integers, small numbers. | Z6: fractions or decimals (that's 1.5); exponents or roots (1.7) | AA6: add_integers
A7: TC005 | B7: 1.2 | C7: Medium | D7: 1 | E7: Multiple choice | F7: A submarine is at a depth of -150 meters. It rises 80 meters, then descends 120 meters. What is its final position relative to sea level? | G7: -50 meters | H7: -10 meters | I7: 10 meters | J7: -190 meters | K7: D) -190 meters | L7: You start at -150. Rising 80 means you add 80: -150 + 80 = -70. Then descending 120 means you subtract 120: -70 - 120 = -190. So the final position is -190 meters. | M7: Start at -150. Rising 80 means add 80, then descending 120 means subtract 120. | N7: agreed | O7: D | X7: Fluently add, subtract, multiply and divide integers. | Y7: Two or three operations, or a short real-life story (temperature, money, elevation). | Z7: fractions or decimals (that's 1.5); exponents or roots (1.7) | AA7: add_integers
A8: TC005 | B8: 1.2 | C8: Medium | D8: 2 | E8: Multiple choice | F8: The temperature was -7°C at 6 a.m. By noon, it had increased by 15°C. Then by 8 p.m., it dropped by 11°C. What was the temperature at 8 p.m.? | G8: -3°C | H8: 3°C | I8: 9°C | J8: 13°C | K8: A) -3°C | L8: Start at -7. Increase by 15: -7 + 15 = 8. Then drop by 11: 8 - 11 = -3. So the temperature at 8 p.m. was -3°C. | M8: Start at -7. Increasing 15 means add 15, then dropping 11 means subtract 11. | N8: agreed | O8: A | X8: Fluently add, subtract, multiply and divide integers. | Y8: Two or three operations, or a short real-life story (temperature, money, elevation). | Z8: fractions or decimals (that's 1.5); exponents or roots (1.7) | AA8: add_integers
A9: TC005 | B9: 1.2 | C9: Medium | D9: 3 | E9: Multiple choice | F9: A stock loses $4 per day for 5 consecutive days. What is the total change in the stock's value? | G9: -9 dollars | H9: -20 dollars | I9: 9 dollars | J9: 20 dollars | K9: B) -20 dollars | L9: Losing $4 each day for 5 days means -4 × 5 = -20. So the total change is -20 dollars. | M9: Losing 4 dollars per day means -4. Multiply that by 5 days. | N9: agreed | O9: B | X9: Fluently add, subtract, multiply and divide integers. | Y9: Two or three operations, or a short real-life story (temperature, money, elevation). | Z9: fractions or decimals (that's 1.5); exponents or roots (1.7) | AA9: multiply_integers
A10: TC005 | B10: 1.2 | C10: Medium | D10: 4 | E10: Multiple choice | F10: A hiker descends 200 feet every hour for 3 hours, then climbs 150 feet. What is her total change in elevation? | G10: -750 feet | H10: -350 feet | I10: -450 feet | J10: 450 feet | K10: C) -450 feet | L10: Descending 200 feet per hour for 3 hours is -200 × 3 = -600. Then climbing 150 feet means +150. So -600 + 150 = -450 feet total change. | M10: Descending 200 feet per hour means -200. Multiply by 3, then add 150 for climbing up. | N10: agreed | O10: C | X10: Fluently add, subtract, multiply and divide integers. | Y10: Two or three operations, or a short real-life story (temperature, money, elevation). | Z10: fractions or decimals (that's 1.5); exponents or roots (1.7) | AA10: multiply_integers
A11: TC005 | B11: 1.2 | C11: Medium | D11: 5 | E11: True/False | F11: The product of two negative integers is always positive. | G11: True | H11: False | K11: A) True | L11: When you multiply two negative integers, like -3 × -4, the result is 12, which is positive. This rule holds for all negative integers. | M11: Think about -2 times -5. Does that make -10 or 10? | N11: agreed | O11: A | X11: Fluently add, subtract, multiply and divide integers. | Y11: Two or three operations, or a short real-life story (temperature, money, elevation). | Z11: fractions or decimals (that's 1.5); exponents or roots (1.7) | AA11: multiply_integers
A12: TC006 | B12: 1.2 | C12: Tricky | D12: 1 | E12: Multiple choice | F12: A submarine is at a depth of -150 meters. It rises 80 meters, then descends 120 meters. What is its final position relative to sea level? | G12: -50 meters | H12: -190 meters | I12: -10 meters | J12: 10 meters | K12: B) -190 meters | L12: You start at -150. Rising 80 means add 80: -150 + 80 = -70. Then descending 120 means subtract 120: -70 - 120 = -190. So the final position is -190 meters. | M12: Start at -150. Rising 80 means add 80, then descending 120 means subtract 120. | N12: agreed | O12: B | X12: Fluently add, subtract, multiply and divide integers. | Y12: Find the correct answer after someone's sign mistake; order of operations with negatives. | Z12: fractions or decimals (that's 1.5); exponents or roots (1.7) | AA12: add_integers
A13: TC006 | B13: 1.2 | C13: Tricky | D13: 2 | E13: Multiple choice | F13: Which expression has the same value as (-7) - (-4)? | G13: -7 + 4 | H13: -7 + (-4) | I13: 7 - 4 | J13: 7 + 4 | K13: A) -7 + 4 | L13: Subtracting a negative is the same as adding the positive. So (-7) - (-4) becomes -7 + 4, which equals -3. The correct expression is -7 + 4. | M13: Subtracting a negative number means you add the positive version of that number. | N13: agreed | O13: A | X13: Fluently add, subtract, multiply and divide integers. | Y13: Find the correct answer after someone's sign mistake; order of operations with negatives. | Z13: fractions or decimals (that's 1.5); exponents or roots (1.7) | AA13: subtract_integers
A14: TC006 | B14: 1.2 | C14: Tricky | D14: 3 | E14: True/False | F14: A student evaluates the expression (-6) × (-3) × (-1). They say the answer is 18. Is this correct? | G14: True | H14: False | K14: B) False | L14: You multiply step by step: (-6) × (-3) = 18, then 18 × (-1) = -18. The correct answer is -18, not 18. Multiplying an odd number of negative integers gives a negative result. | M14: Multiply the first two numbers: negative times negative is positive. Then multiply that result by the third number: positive times negative is negative. | N14: agreed | O14: B | X14: Fluently add, subtract, multiply and divide integers. | Y14: Find the correct answer after someone's sign mistake; order of operations with negatives. | Z14: fractions or decimals (that's 1.5); exponents or roots (1.7) | AA14: multiply_integers
A15: TC006 | B15: 1.2 | C15: Tricky | D15: 4 | E15: Multiple choice | F15: At which step does the error first appear in this work? Problem: (-48) ÷ (-6) ÷ 2. Step 1: (-48) ÷ (-6) = 8. Step 2: 8 ÷ 2 = 4. Step 3: Answer is -4. | G15: Step 1 | H15: Step 2 | I15: There is no error. | J15: Step 3 | K15: D) Step 3 | L15: Steps 1 and 2 are correct: (-48) ÷ (-6) = 8, and 8 ÷ 2 = 4. The answer should be positive 4. The error is in Step 3, where the student incorrectly writes -4 instead of 4. | M15: Check each division step: negative divided by negative is positive, then positive divided by positive is positive. | N15: agreed | O15: D | X15: Fluently add, subtract, multiply and divide integers. | Y15: Find the correct answer after someone's sign mistake; order of operations with negatives. | Z15: fractions or decimals (that's 1.5); exponents or roots (1.7) | AA15: divide_integers
A16: TC006 | B16: 1.2 | C16: Tricky | D16: 5 | E16: Multiple choice | F16: A student evaluates the expression (-5) × (3) + (-4) ÷ (-2). Their work is shown in steps: Step 1: (-5) × 3 = -15 Step 2: (-4) ÷ (-2) = -2 Step 3: -15 + (-2) = -17 At which step does the error first appear? | G16: Step 1 | H16: Step 3 | I16: Step 2 | J16: There is no error | K16: C) Step 2 | L16: You must divide -4 by -2. A negative divided by a negative is positive, so (-4) ÷ (-2) = 2, not -2. The error first appears in Step 2. Then, -15 + 2 = -13, which is the correct final answer. | M16: Divide -4 by -2. Remember, a negative divided by a negative gives a positive result. | N16: agreed | O16: C | X16: Fluently add, subtract, multiply and divide integers. | Y16: Find the correct answer after someone's sign mistake; order of operations with negatives. | Z16: fractions or decimals (that's 1.5); exponents or roots (1.7) | AA16: divide_integers
A17: TC034 | B17: 2.5 | C17: Easy | D17: 1 | E17: Multiple choice | F17: Solve the equation: 2x + 3 = 11 | G17: x = 4 | H17: x = 7 | I17: x = 5 | J17: x = 6 | K17: A) x = 4 | L17: You subtract 3 from both sides to get 2x = 8, then divide both sides by 2 to get x = 4. | M17: Subtract 3 from 11, then divide that answer by 2. | N17: agreed | O17: A | X17: Write, graph, and solve two-step equations and inequalities that include integers and/or rational numbers. | Y17: Solve a two-step equation with small whole numbers. | Z17: variables on both sides, e.g. 8x + 15 = 2x (that's topic 2.6); questions that can only be answered by looking at a picture (a number-line graph described in words is fine) | AA17: solve_two_step_equations
A18: TC034 | B18: 2.5 | C18: Easy | D18: 2 | E18: Multiple choice | F18: Solve the inequality: 3x - 4 > 5 | G18: x > 1 | H18: x > 2 | I18: x > 4 | J18: x > 3 | K18: D) x > 3 | L18: You add 4 to both sides to get 3x > 9, then divide both sides by 3 to get x > 3. | M18: Add 4 to 5, then divide that answer by 3. | N18: agreed | O18: D | X18: Write, graph, and solve two-step equations and inequalities that include integers and/or rational numbers. | Y18: Solve a two-step equation with small whole numbers. | Z18: variables on both sides, e.g. 8x + 15 = 2x (that's topic 2.6); questions that can only be answered by looking at a picture (a number-line graph described in words is fine) | AA18: solve_two_step_inequalities
A19: TC034 | B19: 2.5 | C19: Easy | D19: 3 | E19: Multiple choice | F19: Which inequality represents: 'Five more than twice a number is less than 13'? | G19: 2x - 5 < 13 | H19: 5x + 2 < 13 | I19: 2x + 5 < 13 | J19: 2 + 5x < 13 | K19: C) 2x + 5 < 13 | L19: Twice a number is 2x. Five more than that is 2x + 5. 'Is less than 13' means < 13, so the inequality is 2x + 5 < 13. | M19: Twice a number means 2x. Five more means add 5. Less than means <. | N19: agreed | O19: C | X19: Write, graph, and solve two-step equations and inequalities that include integers and/or rational numbers. | Y19: Solve a two-step equation with small whole numbers. | Z19: variables on both sides, e.g. 8x + 15 = 2x (that's topic 2.6); questions that can only be answered by looking at a picture (a number-line graph described in words is fine) | AA19: write_two_step_inequalities
A20: TC034 | B20: 2.5 | C20: Easy | D20: 4 | E20: Multiple choice | F20: Which equation matches: 'Three less than four times a number equals 13'? | G20: 3 - 4x = 13 | H20: 4x - 3 = 13 | I20: 4x + 3 = 13 | J20: 4(x - 3) = 13 | K20: B) 4x - 3 = 13 | L20: Four times a number is 4x. Three less than that is 4x - 3. Equals 13 means = 13, so the equation is 4x - 3 = 13. | M20: Four times a number means 4x. Three less means subtract 3. Equals means =. | N20: agreed | O20: B | X20: Write, graph, and solve two-step equations and inequalities that include integers and/or rational numbers. | Y20: Solve a two-step equation with small whole numbers. | Z20: variables on both sides, e.g. 8x + 15 = 2x (that's topic 2.6); questions that can only be answered by looking at a picture (a number-line graph described in words is fine) | AA20: write_two_step_equations
A21: TC034 | B21: 2.5 | C21: Easy | D21: 5 | E21: Multiple choice | F21: Solve the equation: -2x + 5 = 1 | G21: x = 2 | H21: x = -2 | I21: x = 3 | J21: x = -3 | K21: A) x = 2 | L21: You subtract 5 from both sides to get -2x = -4. Then divide both sides by -2 to find x = 2. | M21: Start by subtracting 5 from both sides. Then divide by -2. | N21: agreed | O21: A | X21: Write, graph, and solve two-step equations and inequalities that include integers and/or rational numbers. | Y21: Solve a two-step equation with small whole numbers. | Z21: variables on both sides, e.g. 8x + 15 = 2x (that's topic 2.6); questions that can only be answered by looking at a picture (a number-line graph described in words is fine) | AA21: solve_two_step_equations
A22: TC035 | B22: 2.5 | C22: Medium | D22: 1 | E22: Multiple choice | F22: A scuba diver starts at sea level and descends 80 feet. Then, the diver ascends 35 feet. Which equation represents the diver's final position relative to sea level? | G22: x = 80 - 35 | H22: x = -80 - 35 | I22: x = -80 + 35 | J22: x = 35 + 80 | K22: C) x = -80 + 35 | L22: You start at 0. Descending 80 feet means -80. Ascending 35 feet means +35. So the equation is x = -80 + 35. | M22: Start at 0. Descending 80 means -80. Ascending 35 means +35. | N22: agreed | O22: C | X22: Write, graph, and solve two-step equations and inequalities that include integers and/or rational numbers. | Y22: A two-step equation or inequality, sometimes in a short real-life story, with exactly one correct answer. | Z22: variables on both sides, e.g. 8x + 15 = 2x (that's topic 2.6); questions that can only be answered by looking at a picture (a number-line graph described in words is fine) | AA22: write_two_step_equations
A23: TC035 | B23: 2.5 | C23: Medium | D23: 2 | E23: Multiple choice | F23: Solve the inequality: 2x + 5 < 13 | G23: x > 4 | H23: x < 9 | I23: x > 9 | J23: x < 4 | K23: D) x < 4 | L23: Subtract 5 from both sides: 2x < 8. Then divide both sides by 2: x < 4. | M23: Move the 5 to the other side, where it becomes -5. Then divide by 2. | N23: agreed | O23: D | X23: Write, graph, and solve two-step equations and inequalities that include integers and/or rational numbers. | Y23: A two-step equation or inequality, sometimes in a short real-life story, with exactly one correct answer. | Z23: variables on both sides, e.g. 8x + 15 = 2x (that's topic 2.6); questions that can only be answered by looking at a picture (a number-line graph described in words is fine) | AA23: solve_two_step_inequalities
A24: TC035 | B24: 2.5 | C24: Medium | D24: 3 | E24: Multiple choice | F24: The temperature was -10°C at dawn. It rose steadily by 3°C per hour. After how many hours was the temperature 8°C? Write an equation that models this situation. | G24: -10 + 3h = 8 | H24: 10 + 3h = 8 | I24: 3h - 8 = 10 | J24: -10 - 3h = 8 | K24: A) -10 + 3h = 8 | L24: The starting temperature is -10. It increases by 3°C each hour, so after h hours it's -10 + 3h. Set that equal to 8 to find when it reaches 8°C. | M24: Start at -10. Rising 3 per hour means +3h. Set that equal to 8. | N24: agreed | O24: A | X24: Write, graph, and solve two-step equations and inequalities that include integers and/or rational numbers. | Y24: A two-step equation or inequality, sometimes in a short real-life story, with exactly one correct answer. | Z24: variables on both sides, e.g. 8x + 15 = 2x (that's topic 2.6); questions that can only be answered by looking at a picture (a number-line graph described in words is fine) | AA24: write_two_step_equations
A25: TC035 | B25: 2.5 | C25: Medium | D25: 4 | E25: Multiple choice | F25: Which graph correctly shows the solution to the inequality 3x - 6 ≥ 9? | G25: An open circle at 5 with shading to the right | H25: A closed circle at 5 with shading to the right | I25: A closed circle at 1 with shading to the left | J25: An open circle at 1 with shading to the left | K25: B) A closed circle at 5 with shading to the right | L25: Solve: 3x - 6 ≥ 9 → 3x ≥ 15 → x ≥ 5. A closed circle at 5 shows that 5 is included, and shading to the right shows all numbers greater than 5. | M25: Add 6 to both sides, then divide by 3. The inequality sign stays the same. | N25: agreed | O25: B | X25: Write, graph, and solve two-step equations and inequalities that include integers and/or rational numbers. | Y25: A two-step equation or inequality, sometimes in a short real-life story, with exactly one correct answer. | Z25: variables on both sides, e.g. 8x + 15 = 2x (that's topic 2.6); questions that can only be answered by looking at a picture (a number-line graph described in words is fine) | AA25: graph_inequalities
A26: TC035 | B26: 2.5 | C26: Medium | D26: 5 | E26: True/False | F26: Solving the equation 4x + 7 = -13 gives x = -5. | G26: True | H26: False | K26: A) True | L26: Subtract 7 from both sides: 4x = -20. Then divide by 4: x = -5. So the solution is correct. | M26: Move the 7 to the other side, where it becomes -7. Then divide by 4. | N26: agreed | O26: A | X26: Write, graph, and solve two-step equations and inequalities that include integers and/or rational numbers. | Y26: A two-step equation or inequality, sometimes in a short real-life story, with exactly one correct answer. | Z26: variables on both sides, e.g. 8x + 15 = 2x (that's topic 2.6); questions that can only be answered by looking at a picture (a number-line graph described in words is fine) | AA26: solve_two_step_equations
A27: TC036 | B27: 2.5 | C27: Tricky | D27: 1 | E27: Multiple choice | F27: A scuba diver starts at a depth of -150 feet. She rises 80 feet, then descends 120 feet. What is her final depth? | G27: -190 feet | H27: -10 feet | I27: 10 feet | J27: -50 feet | K27: A) -190 feet | L27: You start at -150. Rising 80 feet means adding 80: -150 + 80 = -70. Then descending 120 feet means subtracting 120: -70 - 120 = -190. So the final depth is -190 feet. | M27: Start at -150. Rising 80 means add 80, then descending 120 means subtract 120. | N27: agreed | O27: A | X27: Write, graph, and solve two-step equations and inequalities that include integers and/or rational numbers. | Y27: A two-step inequality where the sign must flip. | Z27: variables on both sides, e.g. 8x + 15 = 2x (that's topic 2.6); questions that can only be answered by looking at a picture (a number-line graph described in words is fine) | AA27: solve_two_step_equations
A28: TC036 | B28: 2.5 | C28: Tricky | D28: 2 | E28: Multiple choice | F28: Which inequality represents the statement: 'Five less than twice a number is at least 14'? | G28: 2x - 5 < 14 | H28: 2x - 5 ≥ 14 | I28: 2x + 5 ≥ 14 | J28: 5 - 2x ≥ 14 | K28: B) 2x - 5 ≥ 14 | L28: Twice a number is 2x. Five less than that is 2x - 5. 'At least 14' means greater than or equal to 14. So the correct inequality is 2x - 5 ≥ 14. | M28: Twice a number means 2x. Five less than that means subtract 5. At least 14 means ≥ 14. | N28: agreed | O28: B | X28: Write, graph, and solve two-step equations and inequalities that include integers and/or rational numbers. | Y28: A two-step inequality where the sign must flip. | Z28: variables on both sides, e.g. 8x + 15 = 2x (that's topic 2.6); questions that can only be answered by looking at a picture (a number-line graph described in words is fine) | AA28: write_two_step_inequalities
A29: TC036 | B29: 2.5 | C29: Tricky | D29: 3 | E29: Multiple choice | F29: Solve the inequality: 3x + 7 < 16 | G29: x > 3 | H29: x < 7 | I29: x > 7 | J29: x < 3 | K29: D) x < 3 | L29: Subtract 7 from both sides: 3x < 9. Then divide both sides by 3: x < 3. The inequality sign stays the same because we divided by a positive number. | M29: Move the 7 to the other side, where it becomes -7. Then divide by 3. | N29: agreed | O29: D | X29: Write, graph, and solve two-step equations and inequalities that include integers and/or rational numbers. | Y29: A two-step inequality where the sign must flip. | Z29: variables on both sides, e.g. 8x + 15 = 2x (that's topic 2.6); questions that can only be answered by looking at a picture (a number-line graph described in words is fine) | AA29: solve_two_step_inequalities
A30: TC036 | B30: 2.5 | C30: Tricky | D30: 4 | E30: Multiple choice | F30: A student solved the equation 4(x - 3) = 20 as shown: Step 1: 4x - 12 = 20 Step 2: 4x = 8 Step 3: x = 2 At which step does the error first appear? | G30: Step 1 | H30: Step 3 | I30: Step 2 | J30: There is no error. | K30: C) Step 2 | L30: Step 1 is correct: distributing 4 gives 4x - 12 = 20. But in Step 2, the student subtracted 12 instead of adding it. The correct step is 4x = 32, so x = 8. The error first appears in Step 2. | M30: Check each step: distribute first, then add 12 to both sides, then divide by 4. | N30: agreed | O30: C | X30: Write, graph, and solve two-step equations and inequalities that include integers and/or rational numbers. | Y30: A two-step inequality where the sign must flip. | Z30: variables on both sides, e.g. 8x + 15 = 2x (that's topic 2.6); questions that can only be answered by looking at a picture (a number-line graph described in words is fine) | AA30: solve_two_step_equations
A31: TC036 | B31: 2.5 | C31: Tricky | D31: 5 | E31: True/False | F31: The solution to the inequality 2x + 5 ≤ 13 is x ≤ 4. | G31: True | H31: False | K31: A) True | L31: Subtract 5 from both sides: 2x ≤ 8. Then divide by 2: x ≤ 4. The solution is correct. | M31: Subtract 5 from both sides, then divide by 2. | N31: agreed | O31: A | X31: Write, graph, and solve two-step equations and inequalities that include integers and/or rational numbers. | Y31: A two-step inequality where the sign must flip. | Z31: variables on both sides, e.g. 8x + 15 = 2x (that's topic 2.6); questions that can only be answered by looking at a picture (a number-line graph described in words is fine) | AA31: solve_two_step_inequalities
A32: TC067 | B32: 3.9 | C32: Easy | D32: 1 | E32: Multiple choice | F32: A shirt costs $20. The store increases the price by 10%. What is the new price? | G32: $20.10 | H32: $30 | I32: $22 | J32: $18 | K32: C) $22 | L32: You find 10% of $20, which is $2, then add it to the original price. $20 + $2 = $22. | M32: 10% of $20 means multiply 20 by 0.10, then add the result to 20. | N32: agreed | O32: C | X32: Solve percent problems involving percentages of increase and decrease (includes mark-up and discount). | Y32: Find a sale price after a simple discount. | Z32: simple or compound interest (not in this objective) | AA32: calculate_percent_increase
A33: TC067 | B33: 3.9 | C33: Easy | D33: 2 | E33: Multiple choice | F33: A book is on sale for 25% off. The original price is $12. What is the sale price? | G33: $9 | H33: $3 | I33: $15 | J33: $11.75 | K33: A) $9 | L33: 25% of $12 is $3. Subtract $3 from $12 to get the sale price: $12 - $3 = $9. | M33: 25% off means multiply 12 by 0.25 to find the discount, then subtract that from 12. | N33: agreed | O33: A | X33: Solve percent problems involving percentages of increase and decrease (includes mark-up and discount). | Y33: Find a sale price after a simple discount. | Z33: simple or compound interest (not in this objective) | AA33: solve_discount_problems
A34: TC067 | B34: 3.9 | C34: Easy | D34: 3 | E34: Multiple choice | F34: A toy costs $40. The price is marked up by 20%. What is the new price? | G34: $50 | H34: $48 | I34: $42 | J34: $32 | K34: B) $48 | L34: 20% of $40 is $8. Add $8 to $40: $40 + $8 = $48. | M34: 20% of 40 means multiply 40 by 0.20, then add the result to 40. | N34: agreed | O34: B | X34: Solve percent problems involving percentages of increase and decrease (includes mark-up and discount). | Y34: Find a sale price after a simple discount. | Z34: simple or compound interest (not in this objective) | AA34: solve_markup_problems
A35: TC067 | B35: 3.9 | C35: Easy | D35: 4 | E35: Multiple choice | F35: A town's population was 800. It decreased by 5%. What is the new population? | G35: 795 | H35: 805 | I35: 750 | J35: 760 | K35: D) 760 | L35: 5% of 800 is 40. Subtract 40 from 800: 800 - 40 = 760. | M35: 5% of 800 means multiply 800 by 0.05, then subtract the result from 800. | N35: agreed | O35: D | X35: Solve percent problems involving percentages of increase and decrease (includes mark-up and discount). | Y35: Find a sale price after a simple discount. | Z35: simple or compound interest (not in this objective) | AA35: calculate_percent_decrease
A36: TC067 | B36: 3.9 | C36: Easy | D36: 5 | E36: True/False | F36: To find the new price after a 15% discount, you multiply the original price by 0.15 and subtract that from the original price. | G36: True | H36: False | K36: A) True | L36: Yes, you find 15% of the price by multiplying by 0.15, then subtract that discount from the original price. | M36: 15% off means multiply the price by 0.15 to get the amount saved, then subtract it. | N36: agreed | O36: A | X36: Solve percent problems involving percentages of increase and decrease (includes mark-up and discount). | Y36: Find a sale price after a simple discount. | Z36: simple or compound interest (not in this objective) | AA36: solve_discount_problems
A37: TC068 | B37: 3.9 | C37: Medium | D37: 1 | E37: Multiple choice | F37: A pair of sneakers originally priced at $80 is on sale for 25% off. What is the sale price of the sneakers? | G37: $75 | H37: $55 | I37: $60 | J37: $70 | K37: C) $60 | L37: You need to find 25% of $80, which is 0.25 × 80 = $20. Then subtract that from the original price: 80 - 20 = $60. So the sale price is $60. | M37: 25% off means multiply 80 by 0.25, then subtract that from 80. | N37: agreed | O37: C | X37: Solve percent problems involving percentages of increase and decrease (includes mark-up and discount). | Y37: Find a selling price after a mark-up. | Z37: simple or compound interest (not in this objective) | AA37: solve_discount_problems
A38: TC068 | B38: 3.9 | C38: Medium | D38: 2 | E38: Multiple choice | F38: A bookstore increases the price of a novel by 20%. If the original price was $15, what is the new price? | G38: $18 | H38: $17 | I38: $19 | J38: $16 | K38: A) $18 | L38: You find 20% of $15, which is 0.20 × 15 = $3. Then add that to the original price: 15 + 3 = $18. So the new price is $18. | M38: 20% increase means multiply 15 by 0.20, then add that to 15. | N38: agreed | O38: A | X38: Solve percent problems involving percentages of increase and decrease (includes mark-up and discount). | Y38: Find a selling price after a mark-up. | Z38: simple or compound interest (not in this objective) | AA38: calculate_percent_increase
A39: TC068 | B39: 3.9 | C39: Medium | D39: 3 | E39: Multiple choice | F39: A jacket is marked down by 30%. If the sale price is $56, what was the original price? | G39: $70 | H39: $75 | I39: $65 | J39: $80 | K39: D) $80 | L39: If the jacket is marked down 30%, you're paying 70% of the original price. So 70% of the original price equals $56. Divide 56 by 0.70: 56 ÷ 0.70 = 80. The original price was $80. | M39: Sale price is 70% of original, so divide 56 by 0.70 to find the original. | N39: agreed | O39: D | X39: Solve percent problems involving percentages of increase and decrease (includes mark-up and discount). | Y39: Find a selling price after a mark-up. | Z39: simple or compound interest (not in this objective) | AA39: solve_discount_problems
A40: TC068 | B40: 3.9 | C40: Medium | D40: 4 | E40: Multiple choice | F40: A store buys a video game for $40 and marks it up by 25% to sell it. What is the selling price? | G40: $45 | H40: $50 | I40: $60 | J40: $55 | K40: B) $50 | L40: You calculate 25% of $40, which is 0.25 × 40 = $10. Then add that to the original cost: 40 + 10 = $50. So the selling price is $50. | M40: 25% markup means multiply 40 by 0.25, then add that to 40. | N40: agreed | O40: B | X40: Solve percent problems involving percentages of increase and decrease (includes mark-up and discount). | Y40: Find a selling price after a mark-up. | Z40: simple or compound interest (not in this objective) | AA40: solve_markup_problems
A41: TC068 | B41: 3.9 | C41: Medium | D41: 5 | E41: True/False | F41: The population of a town increased from 4,000 to 4,600 over one year. The percent increase is 15%. | G41: True | H41: False | K41: A) True | L41: The increase is 4,600 - 4,000 = 600. To find the percent increase: (600 ÷ 4,000) × 100 = 0.15 × 100 = 15%. So the statement is true. | M41: Find the difference, then divide by the original population and multiply by 100. | N41: agreed | O41: A | X41: Solve percent problems involving percentages of increase and decrease (includes mark-up and discount). | Y41: Find a selling price after a mark-up. | Z41: simple or compound interest (not in this objective) | AA41: calculate_percent_increase
A42: TC069 | B42: 3.9 | C42: Tricky | D42: 1 | E42: Multiple choice | F42: A store increases the price of a $45 jacket by 20%. What is the new price of the jacket? | G42: $49 | H42: $54 | I42: $55 | J42: $65 | K42: B) $54 | L42: To find the new price after a 20% increase, multiply 45 by 0.20 to get 9, then add 9 to 45. The new price is $54. | M42: 20% of 45 means multiply 45 by 0.20, then add that to 45. | N42: agreed | O42: B | X42: Solve percent problems involving percentages of increase and decrease (includes mark-up and discount). | Y42: Percent change where the base matters. | Z42: simple or compound interest (not in this objective) | AA42: calculate_percent_increase
A43: TC069 | B43: 3.9 | C43: Tricky | D43: 2 | E43: Multiple choice | F43: A bicycle originally priced at $120 is on sale for 25% off. What is the sale price? | G43: $90 | H43: $100 | I43: $110 | J43: $145 | K43: A) $90 | L43: To find the sale price, calculate 25% of 120, which is 30, then subtract 30 from 120. The sale price is $90. | M43: 25% off means multiply 120 by 0.25, then subtract that from 120. | N43: agreed | O43: A | X43: Solve percent problems involving percentages of increase and decrease (includes mark-up and discount). | Y43: Percent change where the base matters. | Z43: simple or compound interest (not in this objective) | AA43: solve_discount_problems
A44: TC069 | B44: 3.9 | C44: Tricky | D44: 3 | E44: True/False | F44: A student calculated a 15% markup on a $60 item by doing: 60 × 1.5 = 90. Is this correct? | G44: True | H44: False | K44: B) False | L44: No, this is not correct. A 15% markup means multiplying by 1.15, not 1.5. The correct new price is $69, not $90. | M44: 15% increase means multiply by 1 + 0.15, which is 1.15, not 1.5. | N44: agreed | O44: B | X44: Solve percent problems involving percentages of increase and decrease (includes mark-up and discount). | Y44: Percent change where the base matters. | Z44: simple or compound interest (not in this objective) | AA44: solve_markup_problems
A45: TC069 | B45: 3.9 | C45: Tricky | D45: 4 | E45: Multiple choice | F45: Last year, a town had a population of 8,000. This year, it decreased by 6%. What is this year's population? | G45: 7,680 | H45: 7,952 | I45: 8,480 | J45: 7,520 | K45: D) 7,520 | L45: 6% of 8,000 is 480. Subtract 480 from 8,000 to get 7,520. This is the correct population after a 6% decrease. | M45: 6% of 8,000 means multiply 8,000 by 0.06, then subtract that from 8,000. | N45: agreed | O45: D | X45: Solve percent problems involving percentages of increase and decrease (includes mark-up and discount). | Y45: Percent change where the base matters. | Z45: simple or compound interest (not in this objective) | AA45: calculate_percent_decrease
A46: TC069 | B46: 3.9 | C46: Tricky | D46: 5 | E46: Multiple choice | F46: A pair of shoes is marked down from $85 to $68. What percent discount was applied? | G46: 17% | H46: 25% | I46: 20% | J46: 15% | K46: C) 20% | L46: The amount of discount is 85 - 68 = 17. To find the percent, divide 17 by 85 to get 0.20, or 20%. The discount is 20%. | M46: Find how much was taken off, then divide that by the original price and multiply by 100. | N46: agreed | O46: C | X46: Solve percent problems involving percentages of increase and decrease (includes mark-up and discount). | Y46: Percent change where the base matters. | Z46: simple or compound interest (not in this objective) | AA46: solve_discount_problems
A47: TC080 | B47: 4.3 | C47: Medium | D47: 1 | E47: Multiple choice | F47: Two parallel lines are cut by a transversal. One angle measures 75° and is labeled as an alternate exterior angle to angle x. What is the measure of angle x? | G47: 105° | H47: 15° | I47: 115° | J47: 75° | K47: D) 75° | L47: You know that alternate exterior angles are congruent when two parallel lines are cut by a transversal. Since one angle is 75°, angle x must also be 75° because they are alternate exterior angles. | M47: Alternate exterior angles are equal when lines are parallel. So if one is 75°, the other is also 75°. | N47: agreed | O47: D | X47: Classify and determine the measure of angles created when parallel lines are cut by a transversal. | Y47: Use same-side interior angles adding to 180°. | Z47: 'in the figure below' or any other picture reference; triangle sums (4.4) | AA47: classify_angles_transversal
A48: TC080 | B48: 4.3 | C48: Medium | D48: 2 | E48: Multiple choice | F48: In the diagram, two parallel lines are cut by a transversal. Angle A and angle B are same-side interior angles. If angle A measures 110°, what is the measure of angle B? | G48: 110° | H48: 70° | I48: 80° | J48: 90° | K48: B) 70° | L48: Same-side interior angles are supplementary when parallel lines are cut by a transversal. So angle A + angle B = 180°. Since angle A is 110°, angle B must be 180 - 110 = 70°. | M48: Same-side interior angles add up to 180. So subtract 110 from 180 to find angle B. | N48: agreed | O48: B | X48: Classify and determine the measure of angles created when parallel lines are cut by a transversal. | Y48: Use same-side interior angles adding to 180°. | Z48: 'in the figure below' or any other picture reference; triangle sums (4.4) | AA48: calculate_missing_angles
A49: TC080 | B49: 4.3 | C49: Medium | D49: 3 | E49: True/False | F49: When two parallel lines are cut by a transversal, corresponding angles are always equal. | G49: True | H49: False | K49: A) True | L49: You are correct: when two parallel lines are cut by a transversal, corresponding angles are always congruent. This is a key property used to solve many angle problems. | M49: Think about the definition: corresponding angles are in matching corners and are equal when lines are parallel. | N49: agreed | O49: A | X49: Classify and determine the measure of angles created when parallel lines are cut by a transversal. | Y49: Use same-side interior angles adding to 180°. | Z49: 'in the figure below' or any other picture reference; triangle sums (4.4) | AA49: identify_angle_pairs
A50: TC080 | B50: 4.3 | C50: Medium | D50: 4 | E50: Multiple choice | F50: Two parallel lines are cut by a transversal. One angle measures 48° and is adjacent to angle y, forming a straight line. What is the measure of the corresponding angle to angle y? | G50: 132° | H50: 48° | I50: 42° | J50: 96° | K50: A) 132° | L50: Angle y is on a straight line with 48°, so y = 180 - 48 = 132°. The corresponding angle to y will be equal to y because the lines are parallel, so it is also 132°. | M50: First find angle y by subtracting 48 from 180. Then, since corresponding angles are equal, the answer is the same as y. | N50: agreed | O50: A | X50: Classify and determine the measure of angles created when parallel lines are cut by a transversal. | Y50: Use same-side interior angles adding to 180°. | Z50: 'in the figure below' or any other picture reference; triangle sums (4.4) | AA50: apply_parallel_line_properties
A51: TC080 | B51: 4.3 | C51: Medium | D51: 5 | E51: Multiple choice | F51: Angle p and angle q are alternate interior angles formed when two parallel lines are cut by a transversal. If angle p = 3x and angle q = x + 50, what is the value of x? | G51: 20 | H51: 30 | I51: 25 | J51: 15 | K51: C) 25 | L51: Alternate interior angles are equal when lines are parallel, so 3x = x + 50. Subtract x from both sides: 2x = 50. Then divide by 2: x = 25. | M51: Set 3x equal to x + 50 because alternate interior angles are the same. Then solve for x. | N51: agreed | O51: C | X51: Classify and determine the measure of angles created when parallel lines are cut by a transversal. | Y51: Use same-side interior angles adding to 180°. | Z51: 'in the figure below' or any other picture reference; triangle sums (4.4) | AA51: calculate_missing_angles
A52: TC088 | B52: 4.6 | C52: Easy | D52: 1 | E52: Multiple choice | F52: What is the circumference of a circle with a radius of 4 cm? Use pi = 3.14. | G52: 12.56 cm | H52: 25.12 cm | I52: 50.24 cm | J52: 16.0 cm | K52: B) 25.12 cm | L52: You use the formula C = 2 × pi × r. Plug in 4 for r and 3.14 for pi: 2 × 3.14 × 4 = 25.12 cm. | M52: Multiply 2 times 3.14 times 4. | N52: agreed | O52: B | X52: Use values of pi to estimate and calculate the circumference and area of circles. | Y52: Circumference from a diameter, with π given. | Z52: volume (that's 4.9); unstated π values | AA52: calculate_circumference
A53: TC088 | B53: 4.6 | C53: Easy | D53: 2 | E53: Multiple choice | F53: The diameter of a circle is 10 cm. What is its area? Use pi = 3.14. | G53: 78.5 cm² | H53: 31.4 cm² | I53: 314 cm² | J53: 15.7 cm² | K53: A) 78.5 cm² | L53: You use A = pi × r². The radius is half of 10, which is 5. So 3.14 × 5² = 3.14 × 25 = 78.5 cm². | M53: Divide 10 by 2 to get the radius, then multiply 3.14 times 5 times 5. | N53: agreed | O53: A | X53: Use values of pi to estimate and calculate the circumference and area of circles. | Y53: Circumference from a diameter, with π given. | Z53: volume (that's 4.9); unstated π values | AA53: calculate_area
A54: TC088 | B54: 4.6 | C54: Easy | D54: 3 | E54: Multiple choice | F54: A circle has a radius of 7 cm. Estimate its circumference using pi ≈ 3. | G54: 21 cm | H54: 14 cm | I54: 138 cm | J54: 42 cm | K54: D) 42 cm | L54: You use C = 2 × pi × r. With pi ≈ 3 and r = 7, that’s 2 × 3 × 7 = 42 cm. | M54: Multiply 2 times 3 times 7. | N54: agreed | O54: D | X54: Use values of pi to estimate and calculate the circumference and area of circles. | Y54: Circumference from a diameter, with π given. | Z54: volume (that's 4.9); unstated π values | AA54: estimate_circle_measurements
A55: TC088 | B55: 4.6 | C55: Easy | D55: 4 | E55: True/False | F55: To find the area of a circle, you multiply pi by the radius squared. | G55: True | H55: False | K55: A) True | L55: Yes, the formula for area is A = pi × r², so you multiply pi by the radius times itself. | M55: The area formula uses pi and the radius times the radius. | N55: agreed | O55: A | X55: Use values of pi to estimate and calculate the circumference and area of circles. | Y55: Circumference from a diameter, with π given. | Z55: volume (that's 4.9); unstated π values | AA55: use_pi_in_formulas
A56: TC088 | B56: 4.6 | C56: Easy | D56: 5 | E56: Multiple choice | F56: What is the area of a circle with a radius of 3 cm? Use pi = 3.14. | G56: 18.84 cm² | H56: 9.42 cm² | I56: 28.26 cm² | J56: 56.52 cm² | K56: C) 28.26 cm² | L56: You use A = pi × r². So 3.14 × 3² = 3.14 × 9 = 28.26 cm². | M56: Multiply 3.14 times 3 times 3. | N56: agreed | O56: C | X56: Use values of pi to estimate and calculate the circumference and area of circles. | Y56: Circumference from a diameter, with π given. | Z56: volume (that's 4.9); unstated π values | AA56: calculate_area
A57: TC089 | B57: 4.6 | C57: Medium | D57: 1 | E57: Multiple choice | F57: A circular garden has a diameter of 14 meters. What is the approximate circumference of the garden using pi ≈ 3.14? | G57: 43.96 meters | H57: 87.92 meters | I57: 153.86 meters | J57: 615.44 meters | K57: A) 43.96 meters | L57: You use the formula C = π × d. Plug in 3.14 for pi and 14 for the diameter: 3.14 × 14 = 43.96 meters. | M57: Multiply pi (3.14) by the diameter (14). | N57: agreed | O57: A | X57: Use values of pi to estimate and calculate the circumference and area of circles. | Y57: Area from a radius, with π ≈ 22/7 or 3.14 stated in the question. | Z57: volume (that's 4.9); unstated π values | AA57: calculate_circumference
A58: TC089 | B58: 4.6 | C58: Medium | D58: 2 | E58: Multiple choice | F58: The radius of a circular pond is 5 feet. Use pi ≈ 3.14 to estimate the area of the pond. | G58: 31.4 square feet | H58: 62.8 square feet | I58: 78.5 square feet | J58: 157 square feet | K58: C) 78.5 square feet | L58: You use the formula A = π × r². Square the radius (5² = 25), then multiply by 3.14: 3.14 × 25 = 78.5 square feet. | M58: Square the radius (5 × 5), then multiply by 3.14. | N58: agreed | O58: C | X58: Use values of pi to estimate and calculate the circumference and area of circles. | Y58: Area from a radius, with π ≈ 22/7 or 3.14 stated in the question. | Z58: volume (that's 4.9); unstated π values | AA58: calculate_area
A59: TC089 | B59: 4.6 | C59: Medium | D59: 3 | E59: Multiple choice | F59: A circular track has a circumference of about 94.2 meters. Use pi ≈ 3.14 to estimate the diameter of the track. | G59: 15 meters | H59: 47.1 meters | I59: 295.8 meters | J59: 30 meters | K59: D) 30 meters | L59: You use the formula C = π × d. Rearrange to d = C ÷ π. Divide 94.2 by 3.14: 94.2 ÷ 3.14 = 30 meters. | M59: Divide the circumference (94.2) by 3.14 to find the diameter. | N59: agreed | O59: D | X59: Use values of pi to estimate and calculate the circumference and area of circles. | Y59: Area from a radius, with π ≈ 22/7 or 3.14 stated in the question. | Z59: volume (that's 4.9); unstated π values | AA59: estimate_circle_measurements
A60: TC089 | B60: 4.6 | C60: Medium | D60: 4 | E60: Multiple choice | F60: The area of a circle is about 153.86 square inches when pi is approximated as 3.14. What is the radius of the circle? | G60: 14 inches | H60: 7 inches | I60: 24.5 inches | J60: 49 inches | K60: B) 7 inches | L60: You use A = π × r². First divide the area by pi: 153.86 ÷ 3.14 = 49. Then take the square root of 49, which is 7 inches. | M60: Divide the area by 3.14, then find the number that squares to that result. | N60: agreed | O60: B | X60: Use values of pi to estimate and calculate the circumference and area of circles. | Y60: Area from a radius, with π ≈ 22/7 or 3.14 stated in the question. | Z60: volume (that's 4.9); unstated π values | AA60: estimate_circle_measurements
A61: TC089 | B61: 4.6 | C61: Medium | D61: 5 | E61: True/False | F61: To find the area of a circle with radius 6, you can use the formula A = π × r² with pi ≈ 3.14. | G61: True | H61: False | K61: A) True | L61: Yes, the correct formula for the area of a circle is A = π × r². Using pi ≈ 3.14 and r = 6 gives A = 3.14 × 36 = 113.04 square units. | M61: The area formula uses pi times radius squared. | N61: agreed | O61: A | X61: Use values of pi to estimate and calculate the circumference and area of circles. | Y61: Area from a radius, with π ≈ 22/7 or 3.14 stated in the question. | Z61: volume (that's 4.9); unstated π values | AA61: use_pi_in_formulas
A62: TC090 | B62: 4.6 | C62: Tricky | D62: 1 | E62: Multiple choice | F62: A circular garden has a diameter of 14 meters. What is the approximate circumference of the garden using 22/7 for pi? | G62: 22 meters | H62: 88 meters | I62: 44 meters | J62: 154 meters | K62: C) 44 meters | L62: You use the formula C = πd. With d = 14 and π ≈ 22/7, C = (22/7) × 14 = 44 meters. The 14 cancels with the 7 to give 2, then 2 × 22 = 44. | M62: Circumference means the distance around. Use C = πd and replace d with 14 and π with 22/7. | N62: agreed | O62: C | X62: Use values of pi to estimate and calculate the circumference and area of circles. | Y62: Go from circumference to area (find the radius first). | Z62: volume (that's 4.9); unstated π values | AA62: calculate_circumference
A63: TC090 | B63: 4.6 | C63: Tricky | D63: 2 | E63: Multiple choice | F63: A student calculates the area of a circle with radius 10 cm using 3.14 for pi. They write: 3.14 × 10 = 31.4 cm². What is the correct area? | G63: 314 cm² | H63: 31.4 cm² | I63: 62.8 cm² | J63: 628 cm² | K63: A) 314 cm² | L63: You must use A = πr². The radius squared is 10² = 100, so 3.14 × 100 = 314 cm². The student forgot to square the radius. | M63: Area means how much space inside. You need to square the radius first: 10 times 10, then multiply by pi. | N63: agreed | O63: A | X63: Use values of pi to estimate and calculate the circumference and area of circles. | Y63: Go from circumference to area (find the radius first). | Z63: volume (that's 4.9); unstated π values | AA63: calculate_area
A64: TC090 | B64: 4.6 | C64: Tricky | D64: 3 | E64: Multiple choice | F64: A circular pond has a circumference of approximately 66 feet. Using 22/7 for pi, what is the radius of the pond? | G64: 21 feet | H64: 10.5 feet | I64: 33 feet | J64: 132 feet | K64: B) 10.5 feet | L64: Start with C = 2πr. Plug in 66 for C and 22/7 for π: 66 = 2 × (22/7) × r. Simplify: 66 = (44/7)r. Multiply both sides by 7: 462 = 44r. Divide by 44: r = 10.5 feet. | M64: Start with the circumference formula and solve for r. Replace C with 66 and π with 22/7. | N64: agreed | O64: B | X64: Use values of pi to estimate and calculate the circumference and area of circles. | Y64: Go from circumference to area (find the radius first). | Z64: volume (that's 4.9); unstated π values | AA64: calculate_circumference
A65: TC090 | B65: 4.6 | C65: Tricky | D65: 4 | E65: Multiple choice | F65: A pizza has a diameter of 16 inches. About how many square inches of pizza are there? Use 3.14 for pi. | G65: 50.24 in² | H65: 100.48 in² | I65: 803.84 in² | J65: 200.96 in² | K65: D) 200.96 in² | L65: First find the radius: 16 ÷ 2 = 8 inches. Then use A = πr²: 3.14 × 8² = 3.14 × 64 = 200.96 in². | M65: Find the radius by dividing the diameter by 2. Then square it and multiply by pi. | N65: agreed | O65: D | X65: Use values of pi to estimate and calculate the circumference and area of circles. | Y65: Go from circumference to area (find the radius first). | Z65: volume (that's 4.9); unstated π values | AA65: calculate_area
A66: TC090 | B66: 4.6 | C66: Tricky | D66: 5 | E66: True/False | F66: Using 3.14 for pi, the circumference of a circle is about 37.68 cm. A student says the area is about 113.04 cm². Is this correct? | G66: True | H66: False | K66: A) True | L66: You find the radius from C = 2πr: 37.68 = 2 × 3.14 × r → r = 6 cm. Then A = πr² = 3.14 × 36 = 113.04 cm². The student is correct. | M66: Use the circumference to find the radius, then use that radius to find the area. | N66: agreed | O66: A | X66: Use values of pi to estimate and calculate the circumference and area of circles. | Y66: Go from circumference to area (find the radius first). | Z66: volume (that's 4.9); unstated π values | AA66: use_pi_in_formulas
A67: TC120 | B67: 5.5 | C67: Tricky | D67: 1 | E67: Multiple choice | F67: A store tracks how many pairs of shoes it sells each day for a week: 15, 18, 16, 17, 15, 16, 15. The manager wants to report the most common number of shoes sold in a day. Which measure should he use? | G67: Mode | H67: Mean | I67: Median | J67: Range | K67: A) Mode | L67: The mode tells us the value that appears most often. Since the manager wants to know the most common number of shoes sold, the mode (15) is the correct measure to use. | M67: The question asks for the number that happens most often. Which measure finds that? | N67: agreed | O67: A | X67: Select and justify a measure of central tendency (mean, median, or mode) that best represents a set of data. | Y67: Choose and justify the measure for a real decision. | Z67: the word 'best' in the question (the agent rejects questions that use it) | AA67: select_mean_median_mode
A68: TC120 | B68: 5.5 | C68: Tricky | D68: 2 | E68: True/False | F68: A student calculated the mean of the data set 4, 5, 6, 7, 100 and got 24.4. They said this mean represents what most of the data values are like. Is this reasoning correct? | G68: True | H68: False | K68: B) False | L68: The mean is 24.4, but this is much higher than most of the data values because the outlier (100) pulls it up. The mean does not represent what most of the values are like, so the reasoning is incorrect. | M68: Calculate the mean. Then look at the data: is 24.4 close to most of the numbers? | N68: agreed | O68: B | X68: Select and justify a measure of central tendency (mean, median, or mode) that best represents a set of data. | Y68: Choose and justify the measure for a real decision. | Z68: the word 'best' in the question (the agent rejects questions that use it) | AA68: justify_central_tendency
A69: TC120 | B69: 5.5 | C69: Tricky | D69: 3 | E69: Multiple choice | F69: A teacher records test scores for a class: 55, 60, 65, 70, 72, 73, 74, 75, 76, 78, 80. The distribution is nearly symmetric with no outliers. Which measure of central tendency would give a fair summary of the class performance? | G69: Mode, because it shows the score that most students got. | H69: Median, because the data has an outlier. | I69: Range, because it shows how spread out the scores are. | J69: Mean, because the data is symmetric and has no extreme values. | K69: D) Mean, because the data is symmetric and has no extreme values. | L69: When data is symmetric and has no outliers, the mean is a good measure of center because it uses all values and reflects the overall performance fairly. The mean and median will be very close in this case. | M69: Check if the data is balanced on both sides and if any number is much higher or lower than the rest. | N69: agreed | O69: D | X69: Select and justify a measure of central tendency (mean, median, or mode) that best represents a set of data. | Y69: Choose and justify the measure for a real decision. | Z69: the word 'best' in the question (the agent rejects questions that use it) | AA69: justify_central_tendency
A70: TC120 | B70: 5.5 | C70: Tricky | D70: 4 | E70: Multiple choice | F70: A basketball player scored the following points in 7 games: 2, 3, 3, 3, 4, 5, 18. One score is much higher than the others. Which measure of central tendency would give the most accurate summary of her typical performance? | G70: Mean | H70: Median | I70: Mode | J70: Range | K70: B) Median | L70: The median is the middle value when data is ordered, and it is not affected by extreme values. Since 18 is much higher than the other scores, it will pull the mean up and make it less representative. The mode (3) appears most often, but it ignores higher scores. The median (4) best reflects the typical performance. | M70: Put the numbers in order. The score that stands out is much higher than the rest, so think about which measure isn't changed by that big number. | N70: agreed | O70: B | X70: Select and justify a measure of central tendency (mean, median, or mode) that best represents a set of data. | Y70: Choose and justify the measure for a real decision. | Z70: the word 'best' in the question (the agent rejects questions that use it) | AA70: justify_central_tendency
A71: TC120 | B71: 5.5 | C71: Tricky | D71: 5 | E71: Multiple choice | F71: Jamie recorded the number of books read by students in her book club over the summer: 3, 5, 4, 3, 2, 15, 4. One value is much higher than the others. Jamie wants to report a measure that represents a typical number of books read, without being strongly affected by the unusually high value. Which measure should she use? | G71: Mean | H71: Mode | I71: Median | J71: Range | K71: C) Median | L71: The median is the best choice because it is not strongly affected by the outlier (15). It gives a better representation of the typical number of books read. The mean would be pulled higher by the outlier, making it less accurate for typical values. | M71: Look for the number in the middle when the data is ordered. The high value of 15 should not control the result. | N71: agreed | O71: C | X71: Select and justify a measure of central tendency (mean, median, or mode) that best represents a set of data. | Y71: Choose and justify the measure for a real decision. | Z71: the word 'best' in the question (the agent rejects questions that use it) | AA71: justify_central_tendency

Sheet Cases
A1: case_id | B1: topic | C1: level | D1: kind | E1: status | F1: asked | G1: returned | H1: complete? | I1: drafted by AI | J1: passed format check | K1: format pass rate | L1: checked by checker | M1: checker agreed | N1: checker agreement | O1: rejected by checker | P1: attempts | Q1: seconds | R1: letter balance | S1: true/false | T1: retrieval score | U1: expected behaviour | V1: behaviour met? | W1: warnings or error
A2: TC004 | B2: 1.2 | C2: Easy | D2: normal | E2: ok | F2: 5 | G2: 5 | H2: Y | I2: 5 | J2: 5 | K2: =IFERROR(J2/I2,"") -> 1 | L2: 5 | M2: 5 | N2: =IFERROR(M2/L2,"") -> 1 | O2: 0 | P2: 1 | Q2: 20 | R2: 0.25 | S2: 1 | T2: 0.802 | U2: 5 questions | V2: Y
A3: TC005 | B3: 1.2 | C3: Medium | D3: normal | E3: ok | F3: 5 | G3: 5 | H3: Y | I3: 5 | J3: 5 | K3: =IFERROR(J3/I3,"") -> 1 | L3: 5 | M3: 5 | N3: =IFERROR(M3/L3,"") -> 1 | O3: 0 | P3: 1 | Q3: 18.4 | R3: 0.25 | S3: 1 | T3: 0.801 | U3: 5 questions | V3: Y
A4: TC006 | B4: 1.2 | C4: Tricky | D4: normal | E4: ok | F4: 5 | G4: 5 | H4: Y | I4: 6 | J4: 6 | K4: =IFERROR(J4/I4,"") -> 1 | L4: 6 | M4: 5 | N4: =IFERROR(M4/L4,"") -> 0.83333333 | O4: 1 | P4: 2 | Q4: 25.3 | R4: 0.25 | S4: 1 | T4: 0.802 | U4: 5 questions | V4: Y | W4: 1 question(s) rejected by the verifier and regenerated
A5: TC034 | B5: 2.5 | C5: Easy | D5: normal | E5: ok | F5: 5 | G5: 5 | H5: Y | I5: 6 | J5: 5 | K5: =IFERROR(J5/I5,"") -> 0.83333333 | L5: 5 | M5: 5 | N5: =IFERROR(M5/L5,"") -> 1 | O5: 0 | P5: 2 | Q5: 15.5 | R5: 0.4 | S5: 0 | T5: 0.884 | U5: 5 questions | V5: Y
A6: TC035 | B6: 2.5 | C6: Medium | D6: normal | E6: ok | F6: 5 | G6: 5 | H6: Y | I6: 5 | J6: 5 | K6: =IFERROR(J6/I6,"") -> 1 | L6: 5 | M6: 5 | N6: =IFERROR(M6/L6,"") -> 1 | O6: 0 | P6: 2 | Q6: 56.3 | R6: 0.25 | S6: 1 | T6: 0.883 | U6: 5 questions | V6: Y
A7: TC036 | B7: 2.5 | C7: Tricky | D7: normal | E7: ok | F7: 5 | G7: 5 | H7: Y | I7: 5 | J7: 5 | K7: =IFERROR(J7/I7,"") -> 1 | L7: 5 | M7: 5 | N7: =IFERROR(M7/L7,"") -> 1 | O7: 0 | P7: 1 | Q7: 21.1 | R7: 0.25 | S7: 1 | T7: 0.884 | U7: 5 questions | V7: Y
A8: TC067 | B8: 3.9 | C8: Easy | D8: normal | E8: ok | F8: 5 | G8: 5 | H8: Y | I8: 5 | J8: 5 | K8: =IFERROR(J8/I8,"") -> 1 | L8: 5 | M8: 5 | N8: =IFERROR(M8/L8,"") -> 1 | O8: 0 | P8: 1 | Q8: 18.9 | R8: 0.25 | S8: 1 | T8: 0.82 | U8: 5 questions | V8: Y
A9: TC068 | B9: 3.9 | C9: Medium | D9: normal | E9: ok | F9: 5 | G9: 5 | H9: Y | I9: 5 | J9: 5 | K9: =IFERROR(J9/I9,"") -> 1 | L9: 5 | M9: 5 | N9: =IFERROR(M9/L9,"") -> 1 | O9: 0 | P9: 1 | Q9: 25.6 | R9: 0.25 | S9: 1 | T9: 0.82 | U9: 5 questions | V9: Y
A10: TC069 | B10: 3.9 | C10: Tricky | D10: normal | E10: ok | F10: 5 | G10: 5 | H10: Y | I10: 5 | J10: 5 | K10: =IFERROR(J10/I10,"") -> 1 | L10: 5 | M10: 5 | N10: =IFERROR(M10/L10,"") -> 1 | O10: 0 | P10: 1 | Q10: 33.2 | R10: 0.25 | S10: 1 | T10: 0.82 | U10: 5 questions | V10: Y
A11: TC080 | B11: 4.3 | C11: Medium | D11: normal | E11: ok | F11: 5 | G11: 5 | H11: Y | I11: 5 | J11: 5 | K11: =IFERROR(J11/I11,"") -> 1 | L11: 5 | M11: 5 | N11: =IFERROR(M11/L11,"") -> 1 | O11: 0 | P11: 1 | Q11: 20.5 | R11: 0.25 | S11: 1 | T11: 0.797 | U11: 5 questions, each answerable without a picture | V11: Y
A12: TC088 | B12: 4.6 | C12: Easy | D12: normal | E12: ok | F12: 5 | G12: 5 | H12: Y | I12: 5 | J12: 5 | K12: =IFERROR(J12/I12,"") -> 1 | L12: 5 | M12: 5 | N12: =IFERROR(M12/L12,"") -> 1 | O12: 0 | P12: 1 | Q12: 15.3 | R12: 0.25 | S12: 1 | T12: 0.841 | U12: 5 questions | V12: Y
A13: TC089 | B13: 4.6 | C13: Medium | D13: normal | E13: ok | F13: 5 | G13: 5 | H13: Y | I13: 5 | J13: 5 | K13: =IFERROR(J13/I13,"") -> 1 | L13: 5 | M13: 5 | N13: =IFERROR(M13/L13,"") -> 1 | O13: 0 | P13: 1 | Q13: 21.7 | R13: 0.25 | S13: 1 | T13: 0.841 | U13: 5 questions | V13: Y
A14: TC090 | B14: 4.6 | C14: Tricky | D14: normal | E14: ok | F14: 5 | G14: 5 | H14: Y | I14: 5 | J14: 5 | K14: =IFERROR(J14/I14,"") -> 1 | L14: 5 | M14: 5 | N14: =IFERROR(M14/L14,"") -> 1 | O14: 0 | P14: 1 | Q14: 23.7 | R14: 0.25 | S14: 1 | T14: 0.841 | U14: 5 questions | V14: Y
A15: TC120 | B15: 5.5 | C15: Tricky | D15: normal | E15: ok | F15: 5 | G15: 5 | H15: Y | I15: 10 | J15: 5 | K15: =IFERROR(J15/I15,"") -> 0.5 | L15: 5 | M15: 5 | N15: =IFERROR(M15/L15,"") -> 1 | O15: 0 | P15: 4 | Q15: 47.3 | R15: 0.25 | S15: 1 | T15: 0.779 | U15: 5 questions | V15: Y
A16: TC142 | B16: 9.9 | C16: Easy | D16: edge: expect error | E16: error: QuizGenerationError: No sub-unit matching '9.9'. | F16: 5 | G16: 0 | H16: N | I16: 0 | J16: 0 | K16: =IFERROR(J16/I16,"") | L16: 0 | M16: 0 | N16: =IFERROR(M16/L16,"") | O16: 0 | Q16: 0 | S16: 0 | U16: A clear error saying the topic doesn't exist, and no quiz | V16: Y | W16: QuizGenerationError: No sub-unit matching '9.9'.
